<annotation>
	<folder />
	<filename>IMG-4254_jpg.rf.a6527172b6ef4f26b64d84a1157fb1a1.jpg</filename>
	<path>IMG-4254_jpg.rf.a6527172b6ef4f26b64d84a1157fb1a1.jpg</path>
	<source>
		<database>roboflow.com</database>
	</source>
	<size>
		<width>768</width>
		<height>768</height>
		<depth>3</depth>
	</size>
	<segmented>0</segmented>
	<object>
		<name>Healthy</name>
		<pose>Unspecified</pose>
		<truncated>0</truncated>
		<difficult>0</difficult>
		<occluded>0</occluded>
		<bndbox>
			<xmin>697</xmin>
			<xmax>738</xmax>
			<ymin>1</ymin>
			<ymax>21</ymax>
		</bndbox>
		<polygon>
			<x18>697.54175</x18>
			<y18>1.0153909</y18>
			<x19>698.65045</x19>
			<y19>4.061492</y19>
			<x20>697.68176</x20>
			<y20>6.138881</y20>
			<x21>700.4535</x21>
			<y21>13.754129</y21>
			<x22>702.5309</x22>
			<y22>14.722837</y22>
			<x23>703.6395</x23>
			<y23>17.768917</y23>
			<x24>709.87177</x24>
			<y24>20.67504</y24>
			<x25>711.3947</x25>
			<y25>20.120682</y25>
			<x26>712.91785</x26>
			<y26>19.566338</y26>
			<x27>717.07263</x27>
			<y27>21.503754</y27>
			<x28>730.78</x28>
			<y28>16.514658</y28>
			<x29>731.7487</x29>
			<y29>14.437248</y29>
			<x30>738.8097</x30>
			<y30>10.142508</y30>
			</polygon>
	</object>
	<object>
		<name>Healthy</name>
		<pose>Unspecified</pose>
		<truncated>0</truncated>
		<difficult>0</difficult>
		<occluded>0</occluded>
		<bndbox>
			<xmin>730</xmin>
			<xmax>764</xmax>
			<ymin>6</ymin>
			<ymax>33</ymax>
		</bndbox>
		<polygon>
			<x12>742.8244</x12>
			<y12>6.956395</y12>
			<x13>739.7783</x13>
			<y13>8.065098</y13>
			<x14>737.84094</x14>
			<y14>12.21988</y14>
			<x15>734.79486</x15>
			<y15>13.328583</y15>
			<x16>730.92004</x16>
			<y16>21.63815</y16>
			<x17>732.583</x17>
			<y17>26.20728</y17>
			<x18>747.1248</x18>
			<y18>32.98823</y18>
			<x19>748.6478</x19>
			<y19>32.433872</y19>
			<x20>752.2483</x20>
			<y20>32.848236</y20>
			<x21>755.2944</x21>
			<y21>31.739534</y21>
			<x22>759.44916</x22>
			<y22>33.67695</y22>
			<x23>762.49524</x23>
			<y23>32.568268</y23>
			<x24>764.57263</x24>
			<y24>33.536976</y24>
			</polygon>
	</object>
	<object>
		<name>Healthy</name>
		<pose>Unspecified</pose>
		<truncated>0</truncated>
		<difficult>0</difficult>
		<occluded>0</occluded>
		<bndbox>
			<xmin>490</xmin>
			<xmax>519</xmax>
			<ymin>2</ymin>
			<ymax>7</ymax>
		</bndbox>
		<polygon>
			<x14>490.93912</x14>
			<y14>2.0456173</y14>
			<x15>503.40347</x15>
			<y15>7.8578544</y15>
			<x16>504.9265</x16>
			<y16>7.303503</y16>
			<x17>508.52698</x17>
			<y17>7.717868</y17>
			<x18>519.1883</x18>
			<y18>3.8374465</y18>
			</polygon>
	</object>
	<object>
		<name>Healthy</name>
		<pose>Unspecified</pose>
		<truncated>0</truncated>
		<difficult>0</difficult>
		<occluded>0</occluded>
		<bndbox>
			<xmin>353</xmin>
			<xmax>397</xmax>
			<ymin>10</ymin>
			<ymax>57</ymax>
		</bndbox>
		<polygon>
			<x1>395.81577</x1>
			<y1>29.768414</y1>
			<x2>397.75317</x2>
			<y2>25.613651</y2>
			<x3>395.12146</x3>
			<y3>23.121914</y3>
			<x4>394.01276</x4>
			<y4>20.075806</y4>
			<x5>391.93536</x5>
			<y5>19.107098</y5>
			<x6>390.82666</x6>
			<y6>16.060987</y6>
			<x7>378.36234</x7>
			<y7>10.248759</y7>
			<x8>373.79318</x8>
			<y8>11.911826</y8>
			<x9>371.85577</x9>
			<y9>16.066587</y9>
			<x10>368.80966</x10>
			<y10>17.175282</y10>
			<x11>366.87225</x11>
			<y11>21.330044</y11>
			<x12>363.82617</x12>
			<y12>22.438738</y12>
			<x13>361.88873</x13>
			<y13>26.593542</y13>
			<x14>358.84268</x14>
			<y14>27.702244</y14>
			<x15>353.99915</x15>
			<y15>38.08921</y15>
			<x16>355.10785</x16>
			<y16>41.13528</y16>
			<x17>354.13913</x17>
			<y17>43.21268</y17>
			<x18>356.77087</x18>
			<y18>45.70442</y18>
			<x19>357.87958</x19>
			<y19>48.750526</y19>
			<x20>366.18912</x20>
			<y20>52.62535</y20>
			<x21>367.29782</x21>
			<y21>55.67146</y21>
			<x22>371.45258</x22>
			<y22>57.608868</y22>
			<x23>372.97568</x23>
			<y23>57.0545</y23>
			<x24>376.5761</x24>
			<y24>57.46888</y24>
			<x25>379.62216</x25>
			<y25>56.360176</y25>
			<x26>381.69955</x26>
			<y26>57.328884</y26>
			<x27>389.31482</x27>
			<y27>54.557167</y27>
			<x28>393.18964</x28>
			<y28>46.2476</y28>
			<x29>392.08093</x29>
			<y29>43.201492</y29>
			<x30>396.92447</x30>
			<y30>32.81452</y30>
			<x31>395.81577</x31>
			<y31>29.768414</y31>
		</polygon>
	</object>
	<object>
		<name>Healthy</name>
		<pose>Unspecified</pose>
		<truncated>0</truncated>
		<difficult>0</difficult>
		<occluded>0</occluded>
		<bndbox>
			<xmin>391</xmin>
			<xmax>428</xmax>
			<ymin>8</ymin>
			<ymax>62</ymax>
		</bndbox>
		<polygon>
			<x1>426.14236</x1>
			<y1>32.52895</y1>
			<x2>424.06497</x2>
			<y2>31.560244</y2>
			<x3>422.95627</x3>
			<y3>28.514175</y3>
			<x4>417.6928</x4>
			<y4>23.530659</y4>
			<x5>416.02975</x5>
			<y5>18.961512</y5>
			<x6>416.85852</x6>
			<y6>11.760649</y6>
			<x7>416.30414</x7>
			<y7>10.237569</y7>
			<x8>412.14938</x8>
			<y8>8.300162</y8>
			<x9>410.6263</x9>
			<y9>8.854526</y9>
			<x10>408.6889</x10>
			<y10>13.009288</y10>
			<x11>405.64282</x11>
			<y11>14.1179905</y11>
			<x12>404.67413</x12>
			<y12>16.195393</y12>
			<x13>405.78278</x13>
			<y13>19.241493</y13>
			<x14>403.84537</x14>
			<y14>23.396255</y14>
			<x15>396.7845</x15>
			<y15>27.691053</y15>
			<x16>394.84708</x16>
			<y16>31.845816</y16>
			<x17>395.95578</x17>
			<y17>34.891926</y17>
			<x18>393.04965</x18>
			<y18>41.12409</y18>
			<x19>394.15836</x19>
			<y19>44.170197</y19>
			<x20>391.25223</x20>
			<y20>50.402363</y20>
			<x21>394.02396</x21>
			<y21>58.01761</y21>
			<x22>404.41092</x22>
			<y22>62.86114</y22>
			<x23>405.93396</x23>
			<y23>62.30681</y23>
			<x24>409.5344</x24>
			<y24>62.721146</y24>
			<x25>420.19574</x25>
			<y25>58.840733</y25>
			<x26>421.16446</x26>
			<y26>56.76337</y26>
			<x27>424.21054</x27>
			<y27>55.65468</y27>
			<x28>428.0854</x28>
			<y28>47.34511</y28>
			<x29>426.97668</x29>
			<y29>44.299004</y29>
			<x30>427.8054</x30>
			<y30>37.098133</y30>
			<x31>426.14236</x31>
			<y31>32.52895</y31>
		</polygon>
	</object>
	<object>
		<name>Healthy</name>
		<pose>Unspecified</pose>
		<truncated>0</truncated>
		<difficult>0</difficult>
		<occluded>0</occluded>
		<bndbox>
			<xmin>393</xmin>
			<xmax>437</xmax>
			<ymin>79</ymin>
			<ymax>121</ymax>
		</bndbox>
		<polygon>
			<x1>408.98566</x1>
			<y1>80.16904</y1>
			<x2>401.3704</x2>
			<y2>82.94076</y2>
			<x3>400.4017</x3>
			<y3>85.01812</y3>
			<x4>394.3095</x4>
			<y4>87.23551</y4>
			<x5>393.34082</x5>
			<y5>89.31292</y5>
			<x6>395.55817</x6>
			<y6>95.40508</y6>
			<x7>394.58948</x7>
			<y7>97.48249</y7>
			<x8>399.57858</x8>
			<y8>111.18991</y8>
			<x9>401.65598</x9>
			<y9>112.15862</y9>
			<x10>402.76468</x10>
			<y10>115.20473</y10>
			<x11>417.3064</x11>
			<y11>121.985664</y11>
			<x12>418.82944</x12>
			<y12>121.4313</y12>
			<x13>427.96777</x13>
			<y13>118.105255</y13>
			<x14>433.77997</x14>
			<y14>105.64088</y14>
			<x15>432.6713</x15>
			<y15>102.59482</y15>
			<x16>437.51483</x16>
			<y16>92.20785</y16>
			<x17>435.85178</x17>
			<y17>87.63866</y17>
			<x18>419.23264</x18>
			<y18>79.88906</y18>
			<x19>416.18652</x19>
			<y19>80.99775</y19>
			<x20>408.98566</x20>
			<y20>80.16904</y20>
		</polygon>
	</object>
	<object>
		<name>Healthy</name>
		<pose>Unspecified</pose>
		<truncated>0</truncated>
		<difficult>0</difficult>
		<occluded>0</occluded>
		<bndbox>
			<xmin>494</xmin>
			<xmax>538</xmax>
			<ymin>26</ymin>
			<ymax>69</ymax>
		</bndbox>
		<polygon>
			<x1>538.86475</x1>
			<y1>48.4202</y1>
			<x2>534.9843</x2>
			<y2>37.758884</y2>
			<x3>532.9069</x3>
			<y3>36.790176</y3>
			<x4>531.7983</x4>
			<y4>33.744076</y4>
			<x5>527.64343</x5>
			<y5>31.806662</y5>
			<x6>526.5347</x6>
			<y6>28.760572</y6>
			<x7>522.38</x7>
			<y7>26.823166</y7>
			<x8>519.33386</x8>
			<y8>27.93186</y8>
			<x9>517.2565</x9>
			<y9>26.963152</y9>
			<x10>511.1643</x10>
			<y10>29.180529</y10>
			<x11>507.0095</x11>
			<y11>27.243113</y11>
			<x12>502.44037</x12>
			<y12>28.906137</y12>
			<x13>500.50296</x13>
			<y13>33.06094</y13>
			<x14>497.45685</x14>
			<y14>34.169636</y14>
			<x15>494.55072</x15>
			<y15>40.4018</y15>
			<x16>497.87683</x16>
			<y16>49.540085</y16>
			<x17>496.9081</x17>
			<y17>51.61749</y17>
			<x18>501.89722</x18>
			<y18>65.32491</y18>
			<x19>503.97458</x19>
			<y19>66.29361</y19>
			<x20>505.08328</x20>
			<y20>69.33972</y20>
			<x21>506.60635</x21>
			<y21>68.7854</y21>
			<x22>510.2068</x22>
			<y22>69.19974</y22>
			<x23>525.43726</x23>
			<y23>63.65629</y23>
			<x24>527.51465</x24>
			<y24>64.625</y24>
			<x25>532.0838</x25>
			<y25>62.96197</y25>
			<x26>534.9899</x26>
			<y26>56.72981</y26>
			<x27>538.036</x27>
			<y27>55.621113</y27>
			<x28>536.9273</x28>
			<y28>52.575005</y28>
			<x29>538.86475</x29>
			<y29>48.4202</y29>
		</polygon>
	</object>
	<object>
		<name>Healthy</name>
		<pose>Unspecified</pose>
		<truncated>0</truncated>
		<difficult>0</difficult>
		<occluded>0</occluded>
		<bndbox>
			<xmin>550</xmin>
			<xmax>604</xmax>
			<ymin>8</ymin>
			<ymax>56</ymax>
		</bndbox>
		<polygon>
			<x1>599.65234</x1>
			<y1>40.093884</y1>
			<x2>597.5749</x2>
			<y2>39.125168</y2>
			<x3>595.91187</x3>
			<y3>34.55603</y3>
			<x4>596.88055</x4>
			<y4>32.478626</y4>
			<x5>594.24884</x5>
			<y5>29.986868</y5>
			<x6>590.9227</x6>
			<y6>20.848581</y6>
			<x7>586.768</x7>
			<y7>18.911175</y7>
			<x8>585.6593</x8>
			<y8>15.865066</y8>
			<x9>579.4271</x9>
			<y9>12.958972</y9>
			<x10>578.3184</x10>
			<y10>9.912863</y10>
			<x11>576.241</x11>
			<y11>8.944155</y11>
			<x12>573.1949</x12>
			<y12>10.05285</y12>
			<x13>569.04016</x13>
			<y13>8.115442</y13>
			<x14>566.5484</x14>
			<y14>10.747167</y14>
			<x15>560.4562</x15>
			<y15>12.964563</y15>
			<x16>550.76917</x16>
			<y16>33.738476</y16>
			<x17>552.4322</x17>
			<y17>38.307625</y17>
			<x18>554.5096</x18>
			<y18>39.276325</y18>
			<x19>556.7269</x19>
			<y19>45.36854</y19>
			<x20>581.65564</x20>
			<y20>56.992966</y20>
			<x21>583.1787</x21>
			<y21>56.438644</y21>
			<x22>589.27094</x22>
			<y22>54.22125</y22>
			<x23>590.2396</x23>
			<y23>52.143845</y23>
			<x24>594.8088</x24>
			<y24>50.48082</y24>
			<x25>601.04095</x25>
			<y25>53.386944</y25>
			<x26>602.56396</x26>
			<y26>52.832607</y26>
			<x27>604.50134</x27>
			<y27>48.677803</y27>
			<x28>601.8696</x28>
			<y28>46.186066</y28>
			<x29>599.65234</x29>
			<y29>40.093884</y29>
		</polygon>
	</object>
	<object>
		<name>Healthy</name>
		<pose>Unspecified</pose>
		<truncated>0</truncated>
		<difficult>0</difficult>
		<occluded>0</occluded>
		<bndbox>
			<xmin>588</xmin>
			<xmax>657</xmax>
			<ymin>118</ymin>
			<ymax>182</ymax>
		</bndbox>
		<polygon>
			<x1>648.98895</x1>
			<y1>175.64519</y1>
			<x2>652.03503</x2>
			<y2>174.53651</y2>
			<x3>653.0038</x3>
			<y3>172.45912</y3>
			<x4>651.895</x4>
			<y4>169.41301</y4>
			<x5>653.83246</x5>
			<y5>165.25821</y5>
			<x6>652.7238</x6>
			<y6>162.21214</y6>
			<x7>656.59863</x7>
			<y7>153.90257</y7>
			<x8>655.48987</x8>
			<y8>150.85646</y8>
			<x9>657.4273</x9>
			<y9>146.70166</y9>
			<x10>656.3186</x10>
			<y10>143.6556</y10>
			<x11>657.2873</x11>
			<y11>141.57819</y11>
			<x12>652.29816</x12>
			<y12>127.87072</y12>
			<x13>650.2209</x13>
			<y13>126.90203</y13>
			<x14>649.1121</x14>
			<y14>123.85596</y14>
			<x15>636.64777</x15>
			<y15>118.043724</y15>
			<x16>633.6016</x16>
			<y16>119.15241</y16>
			<x17>631.52423</x17>
			<y17>118.18371</y17>
			<x18>628.47815</x18>
			<y18>119.292404</y18>
			<x19>621.2773</x19>
			<y19>118.46365</y19>
			<x20>618.7856</x20>
			<y20>121.09543</y20>
			<x21>612.69336</x21>
			<y21>123.312775</y21>
			<x22>611.7247</x22>
			<y22>125.39018</y22>
			<x23>608.6785</x23>
			<y23>126.49887</y23>
			<x24>607.7099</x24>
			<y24>128.57628</y24>
			<x25>604.66376</x25>
			<y25>129.68492</y25>
			<x26>603.69507</x26>
			<y26>131.76233</y26>
			<x27>596.63416</x27>
			<y27>136.05713</y27>
			<x28>588.8845</x28>
			<y28>152.67627</y28>
			<x29>593.3192</x29>
			<y29>164.86064</y29>
			<x30>592.3506</x30>
			<y30>166.93805</y30>
			<x31>595.1223</x31>
			<y31>174.55325</y31>
			<x32>609.664</x32>
			<y32>181.3342</y32>
			<x33>611.1871</x33>
			<y33>180.77988</y33>
			<x34>612.7102</x34>
			<y34>180.22551</y34>
			<x35>616.8649</x35>
			<y35>182.1629</y35>
			<x36>625.0345</x36>
			<y36>180.91428</y36>
			<x37>629.18933</x37>
			<y37>182.85168</y37>
			<x38>635.28143</x38>
			<y38>180.63428</y38>
			<x39>637.3588</x39>
			<y39>181.60298</y39>
			<x40>648.0202</x40>
			<y40>177.72258</y40>
			<x41>648.98895</x41>
			<y41>175.64519</y41>
		</polygon>
	</object>
	<object>
		<name>Healthy</name>
		<pose>Unspecified</pose>
		<truncated>0</truncated>
		<difficult>0</difficult>
		<occluded>0</occluded>
		<bndbox>
			<xmin>579</xmin>
			<xmax>612</xmax>
			<ymin>100</ymin>
			<ymax>134</ymax>
		</bndbox>
		<polygon>
			<x1>608.533</x1>
			<y1>102.40449</y1>
			<x2>604.3782</x2>
			<y2>100.46707</y2>
			<x3>601.33215</x3>
			<y3>101.575775</y3>
			<x4>594.13116</x4>
			<y4>100.747</y4>
			<x5>586.516</x5>
			<y5>103.51873</y5>
			<x6>579.73505</x6>
			<y6>118.0605</y6>
			<x7>580.8437</x7>
			<y7>121.106606</y7>
			<x8>579.875</x8>
			<y8>123.18397</y8>
			<x9>581.538</x9>
			<y9>127.75315</y9>
			<x10>583.6154</x10>
			<y10>128.72186</y10>
			<x11>584.7242</x11>
			<y11>131.76793</y11>
			<x12>590.9563</x12>
			<y12>134.67404</y12>
			<x13>592.4794</x13>
			<y13>134.11972</y13>
			<x14>596.0798</x14>
			<y14>134.53404</y14>
			<x15>600.649</x15>
			<y15>132.87103</y15>
			<x16>601.6177</x16>
			<y16>130.79362</y16>
			<x17>608.6785</x17>
			<y17>126.49887</y17>
			<x18>612.55334</x18>
			<y18>118.1893</y18>
			<x19>611.4447</x19>
			<y19>115.1432</y19>
			<x20>612.4134</x20>
			<y20>113.065796</y20>
			<x21>608.533</x21>
			<y21>102.40449</y21>
		</polygon>
	</object>
	<object>
		<name>Healthy</name>
		<pose>Unspecified</pose>
		<truncated>0</truncated>
		<difficult>0</difficult>
		<occluded>0</occluded>
		<bndbox>
			<xmin>643</xmin>
			<xmax>693</xmax>
			<ymin>99</ymin>
			<ymax>134</ymax>
		</bndbox>
		<polygon>
			<x1>687.7427</x1>
			<y1>111.52038</y1>
			<x2>691.89746</x2>
			<y2>113.457794</y2>
			<x3>693.42053</x3>
			<y3>112.903435</y3>
			<x4>691.75745</x4>
			<y4>108.33428</y4>
			<x5>685.5253</x5>
			<y5>105.42818</y5>
			<x6>684.4166</x6>
			<y6>102.3821</y6>
			<x7>678.1845</x7>
			<y7>99.476</y7>
			<x8>675.1383</x8>
			<y8>100.58469</y8>
			<x9>673.0609</x9>
			<y9>99.615974</y9>
			<x10>666.9688</x10>
			<y10>101.833336</y10>
			<x11>664.8914</x11>
			<y11>100.86463</y11>
			<x12>660.32227</x12>
			<y12>102.527695</y12>
			<x13>659.3535</x13>
			<y13>104.60505</y13>
			<x14>650.2152</x14>
			<y14>107.93114</y14>
			<x15>649.2466</x15>
			<y15>110.00855</y15>
			<x16>646.20044</x16>
			<y16>111.117195</y16>
			<x17>643.2943</x17>
			<y17>117.34941</y17>
			<x18>644.95734</x18>
			<y18>121.91854</y18>
			<x19>649.1121</x19>
			<y19>123.85596</y19>
			<x20>650.2209</x20>
			<y20>126.90203</y20>
			<x21>654.3756</x21>
			<y21>128.83943</y21>
			<x22>655.4843</x22>
			<y22>131.88554</y22>
			<x23>659.63904</x23>
			<y23>133.82295</y23>
			<x24>661.1621</x24>
			<y24>133.26863</y24>
			<x25>662.6852</x25>
			<y25>132.71426</y25>
			<x26>666.84</x26>
			<y26>134.65167</y26>
			<x27>674.4552</x27>
			<y27>131.87994</y27>
			<x28>675.42395</x28>
			<y28>129.80255</y28>
			<x29>678.47003</x29>
			<y29>128.6939</y29>
			<x30>684.2822</x30>
			<y30>116.22952</y30>
			<x31>683.1735</x31>
			<y31>113.1834</y31>
			<x32>687.7427</x32>
			<y32>111.52038</y32>
		</polygon>
	</object>
	<object>
		<name>Healthy</name>
		<pose>Unspecified</pose>
		<truncated>0</truncated>
		<difficult>0</difficult>
		<occluded>0</occluded>
		<bndbox>
			<xmin>644</xmin>
			<xmax>713</xmax>
			<ymin>98</ymin>
			<ymax>156</ymax>
		</bndbox>
		<polygon>
			<x1>712.53705</x1>
			<y1>136.99228</y1>
			<x2>713.5057</x2>
			<y2>134.91487</y2>
			<x3>709.6253</x3>
			<y3>124.25352</y3>
			<x4>705.4705</x4>
			<y4>122.3161</y4>
			<x5>704.3619</x5>
			<y5>119.27004</y5>
			<x6>698.12964</x6>
			<y6>116.36392</y6>
			<x7>697.02094</x7>
			<y7>113.3178</y7>
			<x8>694.9436</x8>
			<y8>112.34911</y8>
			<x9>690.6488</x9>
			<y9>105.28822</y9>
			<x10>676.10706</x10>
			<y10>98.507286</y10>
			<x11>666.9688</x11>
			<y11>101.833336</y11>
			<x12>664.8914</x12>
			<y12>100.86463</y12>
			<x13>660.32227</x13>
			<y13>102.527695</y13>
			<x14>659.3535</x14>
			<y14>104.60505</y14>
			<x15>650.2152</x15>
			<y15>107.93114</y15>
			<x16>649.2466</x16>
			<y16>110.00855</y16>
			<x17>646.20044</x17>
			<y17>111.117195</y17>
			<x18>644.263</x18>
			<y18>115.271996</y18>
			<x19>647.0347</x19>
			<y19>122.887245</y19>
			<x20>649.1121</x20>
			<y20>123.85596</y20>
			<x21>650.2209</x21>
			<y21>126.90203</y21>
			<x22>654.3756</x22>
			<y22>128.83943</y22>
			<x23>655.4843</x23>
			<y23>131.88554</y23>
			<x24>659.63904</x24>
			<y24>133.82295</y24>
			<x25>662.6852</x25>
			<y25>132.71426</y25>
			<x26>666.84</x26>
			<y26>134.65167</y26>
			<x27>669.3317</x27>
			<y27>132.01994</y27>
			<x28>672.9321</x28>
			<y28>132.43431</y28>
			<x29>674.5952</x29>
			<y29>137.00346</y29>
			<x30>672.6578</x30>
			<y30>141.15822</y30>
			<x31>675.4295</x31>
			<y31>148.77347</y31>
			<x32>677.5069</x32>
			<y32>149.74217</y32>
			<x33>678.61554</x33>
			<y33>152.78828</y33>
			<x34>682.21606</x34>
			<y34>153.20262</y34>
			<x35>685.8164</x35>
			<y35>153.61699</y35>
			<x36>688.8626</x36>
			<y36>152.5083</y36>
			<x37>697.1721</x37>
			<y37>156.38312</y37>
			<x38>700.21826</x38>
			<y38>155.27443</y38>
			<x39>702.29565</x39>
			<y39>156.24313</y39>
			<x40>706.8648</x40>
			<y40>154.58011</y40>
			<x41>713.6457</x41>
			<y41>140.03833</y41>
			<x42>712.53705</x42>
			<y42>136.99228</y42>
		</polygon>
	</object>
	<object>
		<name>Healthy</name>
		<pose>Unspecified</pose>
		<truncated>0</truncated>
		<difficult>0</difficult>
		<occluded>0</occluded>
		<bndbox>
			<xmin>664</xmin>
			<xmax>700</xmax>
			<ymin>152</ymin>
			<ymax>194</ymax>
		</bndbox>
		<polygon>
			<x1>688.8626</x1>
			<y1>152.5083</y1>
			<x2>685.8164</x2>
			<y2>153.61699</y2>
			<x3>683.73914</x3>
			<y3>152.6483</y3>
			<x4>671.5547</x4>
			<y4>157.08304</y4>
			<x5>667.9543</x5>
			<y5>156.6687</y5>
			<x6>666.0169</x6>
			<y6>160.82347</y6>
			<x7>667.12555</x7>
			<y7>163.86957</y7>
			<x8>664.2195</x8>
			<y8>170.10175</y8>
			<x9>665.88245</x9>
			<y9>174.67087</y9>
			<x10>667.95984</x10>
			<y10>175.63959</y10>
			<x11>669.0685</x11>
			<y11>178.68568</y11>
			<x12>671.1459</x12>
			<y12>179.65439</y12>
			<x13>672.25464</x13>
			<y13>182.7005</y13>
			<x14>674.33203</x14>
			<y14>183.66922</y14>
			<x15>678.6268</x15>
			<y15>190.73009</y15>
			<x16>686.93634</x16>
			<y16>194.60492</y16>
			<x17>688.4594</x17>
			<y17>194.0506</y17>
			<x18>691.5055</x18>
			<y18>192.9419</y18>
			<x19>700.2238</x19>
			<y19>174.24535</y19>
			<x20>699.1152</x20>
			<y20>171.19925</y20>
			<x21>700.0838</x21>
			<y21>169.12184</y21>
			<x22>696.2034</x22>
			<y22>158.46053</y22>
			<x23>694.12604</x23>
			<y23>157.49182</y23>
			<x24>693.0174</x24>
			<y24>154.44572</y24>
			<x25>688.8626</x25>
			<y25>152.5083</y25>
		</polygon>
	</object>
	<object>
		<name>Healthy</name>
		<pose>Unspecified</pose>
		<truncated>0</truncated>
		<difficult>0</difficult>
		<occluded>0</occluded>
		<bndbox>
			<xmin>638</xmin>
			<xmax>680</xmax>
			<ymin>174</ymin>
			<ymax>207</ymax>
		</bndbox>
		<polygon>
			<x1>671.1459</x1>
			<y1>179.65439</y1>
			<x2>660.759</x2>
			<y2>174.81087</y2>
			<x3>657.7128</x3>
			<y3>175.91956</y3>
			<x4>655.6355</x4>
			<y4>174.95087</y4>
			<x5>648.0202</x5>
			<y5>177.72258</y5>
			<x6>647.0516</x6>
			<y6>179.79999</y6>
			<x7>640.95935</x7>
			<y7>182.01738</y7>
			<x8>638.0532</x8>
			<y8>188.24954</y8>
			<x9>641.93365</x9>
			<y9>198.91086</y9>
			<x10>644.01105</x10>
			<y10>199.87956</y10>
			<x11>645.1197</x11>
			<y11>202.92566</y11>
			<x12>655.5067</x12>
			<y12>207.7692</y12>
			<x13>657.02966</x13>
			<y13>207.21486</y13>
			<x14>660.6302</x14>
			<y14>207.62921</y14>
			<x15>663.6762</x15>
			<y15>206.52051</y15>
			<x16>665.75366</x16>
			<y16>207.48921</y16>
			<x17>670.32275</x17>
			<y17>205.82619</y17>
			<x18>680.2898</x18>
			<y18>195.29922</y18>
			<x19>676.4094</x19>
			<y19>184.63792</y19>
			<x20>672.25464</x20>
			<y20>182.7005</y20>
			<x21>671.1459</x21>
			<y21>179.65439</y21>
		</polygon>
	</object>
	<object>
		<name>Healthy</name>
		<pose>Unspecified</pose>
		<truncated>0</truncated>
		<difficult>0</difficult>
		<occluded>0</occluded>
		<bndbox>
			<xmin>566</xmin>
			<xmax>618</xmax>
			<ymin>209</ymin>
			<ymax>261</ymax>
		</bndbox>
		<polygon>
			<x1>614.25555</x1>
			<y1>255.55482</y1>
			<x2>617.1617</x2>
			<y2>249.32266</y2>
			<x3>616.053</x3>
			<y3>246.27655</y3>
			<x4>617.0217</x4>
			<y4>244.19916</y4>
			<x5>615.77295</x5>
			<y5>236.02957</y5>
			<x6>618.67914</x6>
			<y6>229.79738</y6>
			<x7>617.5704</x7>
			<y7>226.7513</y7>
			<x8>618.3992</x8>
			<y8>219.55038</y8>
			<x9>615.76746</x9>
			<y9>217.05865</y9>
			<x10>614.65875</x10>
			<y10>214.01256</y10>
			<x11>612.58136</x11>
			<y11>213.04384</y11>
			<x12>611.47266</x12>
			<y12>209.99777</y12>
			<x13>608.4266</x13>
			<y13>211.10643</y13>
			<x14>606.3492</x14>
			<y14>210.13773</y14>
			<x15>591.11865</x15>
			<y15>215.68117</y15>
			<x16>589.04126</x16>
			<y16>214.7125</y16>
			<x17>581.426</x17>
			<y17>217.48422</y17>
			<x18>580.45734</x18>
			<y18>219.56157</y18>
			<x19>574.3652</x19>
			<y19>221.77898</y19>
			<x20>573.3964</x20>
			<y20>223.85637</y20>
			<x21>570.35034</x21>
			<y21>224.96507</y21>
			<x22>567.4442</x22>
			<y22>231.19724</y22>
			<x23>568.5529</x23>
			<y23>234.24335</y23>
			<x24>566.61554</x24>
			<y24>238.39812</y24>
			<x25>571.6046</x25>
			<y25>252.10558</y25>
			<x26>573.68195</x26>
			<y26>253.07426</y26>
			<x27>574.7907</x27>
			<y27>256.12033</y27>
			<x28>581.0229</x28>
			<y28>259.02646</y28>
			<x29>582.5459</x29>
			<y29>258.47214</y29>
			<x30>586.14636</x30>
			<y30>258.88647</y30>
			<x31>589.19244</x31>
			<y31>257.77777</y31>
			<x32>595.4247</x32>
			<y32>260.6839</y32>
			<x33>598.4707</x33>
			<y33>259.57523</y33>
			<x34>602.62555</x34>
			<y34>261.5126</y34>
			<x35>610.2407</x35>
			<y35>258.74088</y35>
			<x36>611.2095</x36>
			<y36>256.6635</y36>
			<x37>614.25555</x37>
			<y37>255.55482</y37>
		</polygon>
	</object>
	<object>
		<name>Healthy</name>
		<pose>Unspecified</pose>
		<truncated>0</truncated>
		<difficult>0</difficult>
		<occluded>0</occluded>
		<bndbox>
			<xmin>558</xmin>
			<xmax>600</xmax>
			<ymin>176</ymin>
			<ymax>219</ymax>
		</bndbox>
		<polygon>
			<x1>590.1388</x1>
			<y1>179.81677</y1>
			<x2>583.9066</x2>
			<y2>176.91064</y2>
			<x3>580.86053</x3>
			<y3>178.01935</y3>
			<x4>576.70575</x4>
			<y4>176.08192</y4>
			<x5>566.0444</x5>
			<y5>179.96234</y5>
			<x6>565.0757</x6>
			<y6>182.03975</y6>
			<x7>562.0296</x7>
			<y7>183.14839</y7>
			<x8>558.1547</x8>
			<y8>191.45796</y8>
			<x9>559.2634</x9>
			<y9>194.50407</y9>
			<x10>558.29474</x10>
			<y10>196.58148</y10>
			<x11>559.9578</x11>
			<y11>201.15062</y11>
			<x12>562.03516</x12>
			<y12>202.11932</y12>
			<x13>564.25256</x13>
			<y13>208.21153</y13>
			<x14>566.3299</x14>
			<y14>209.18019</y14>
			<x15>568.5473</x15>
			<y15>215.27242</y15>
			<x16>576.85693</x16>
			<y16>219.14725</y16>
			<x17>578.3799</x17>
			<y17>218.59286</y17>
			<x18>596.65656</x18>
			<y18>211.94073</y18>
			<x19>597.62524</x19>
			<y19>209.86337</y19>
			<x20>600.6714</x20>
			<y20>208.75468</y20>
			<x21>596.2366</x21>
			<y21>196.5703</y21>
			<x22>597.20526</x22>
			<y22>194.49289</y22>
			<x23>594.43353</x23>
			<y23>186.87764</y23>
			<x24>592.35614</x24>
			<y24>185.90892</y24>
			<x25>590.1388</x25>
			<y25>179.81677</y25>
		</polygon>
	</object>
	<object>
		<name>Healthy</name>
		<pose>Unspecified</pose>
		<truncated>0</truncated>
		<difficult>0</difficult>
		<occluded>0</occluded>
		<bndbox>
			<xmin>532</xmin>
			<xmax>572</xmax>
			<ymin>195</ymin>
			<ymax>242</ymax>
		</bndbox>
		<polygon>
			<x1>559.9578</x1>
			<y1>201.15062</y1>
			<x2>558.8491</x2>
			<y2>198.1045</y2>
			<x3>556.7717</x3>
			<y3>197.1358</y3>
			<x4>553.7256</x4>
			<y4>198.2445</y4>
			<x5>547.4934</x5>
			<y5>195.33838</y5>
			<x6>536.8321</x6>
			<y6>199.2188</y6>
			<x7>533.92596</x7>
			<y7>205.45096</y7>
			<x8>535.03467</x8>
			<y8>208.49707</y8>
			<x9>532.12854</x9>
			<y9>214.72928</y9>
			<x10>533.23724</x10>
			<y10>217.77534</y10>
			<x11>532.26855</x11>
			<y11>219.85275</y11>
			<x12>533.9316</x12>
			<y12>224.42189</y12>
			<x13>536.009</x13>
			<y13>225.3906</y13>
			<x14>538.2263</x14>
			<y14>231.48282</y14>
			<x15>540.3038</x15>
			<y15>232.45152</y15>
			<x16>541.4124</x16>
			<y16>235.49757</y16>
			<x17>555.95416</x17>
			<y17>242.27852</y17>
			<x18>557.47723</x18>
			<y18>241.7242</y18>
			<x19>566.61554</x19>
			<y19>238.39812</y19>
			<x20>567.5842</x20>
			<y20>236.3207</y20>
			<x21>566.4755</x21>
			<y21>233.27464</y21>
			<x22>572.2878</x22>
			<y22>220.81027</y22>
			<x23>569.51605</x23>
			<y23>213.19502</y23>
			<x24>564.25256</x24>
			<y24>208.21153</y24>
			<x25>562.03516</x25>
			<y25>202.11932</y25>
			<x26>559.9578</x26>
			<y26>201.15062</y26>
		</polygon>
	</object>
	<object>
		<name>Healthy</name>
		<pose>Unspecified</pose>
		<truncated>0</truncated>
		<difficult>0</difficult>
		<occluded>0</occluded>
		<bndbox>
			<xmin>498</xmin>
			<xmax>547</xmax>
			<ymin>136</ymin>
			<ymax>214</ymax>
		</bndbox>
		<polygon>
			<x1>544.8617</x1>
			<y1>192.84665</y1>
			<x2>547.7678</x2>
			<y2>186.61449</y2>
			<x3>546.6591</x3>
			<y3>183.56837</y3>
			<x4>547.48785</x4>
			<y4>176.36751</y4>
			<x5>544.85614</x5>
			<y5>173.87572</y5>
			<x6>540.4213</x6>
			<y6>161.69133</y6>
			<x7>536.26654</x7>
			<y7>159.75392</y7>
			<x8>533.4949</x8>
			<y8>152.13867</y8>
			<x9>534.46356</x9>
			<y9>150.06131</y9>
			<x10>529.4744</x10>
			<y10>136.35385</y10>
			<x11>526.42834</x11>
			<y11>137.46254</y11>
			<x12>524.35095</x12>
			<y12>136.49384</y12>
			<x13>519.7818</x13>
			<y13>138.15686</y13>
			<x14>516.87573</x14>
			<y14>144.38907</y14>
			<x15>517.9844</x15>
			<y15>147.43517</y15>
			<x16>516.047</x16>
			<y16>151.58994</y16>
			<x17>517.15564</x17>
			<y17>154.63605</y17>
			<x18>515.21826</x18>
			<y18>158.7908</y18>
			<x19>512.1722</x19>
			<y19>159.8995</y19>
			<x20>511.20346</x20>
			<y20>161.97691</y20>
			<x21>508.15735</x21>
			<y21>163.0856</y21>
			<x22>506.21994</x22>
			<y22>167.24037</y22>
			<x23>503.17383</x23>
			<y23>168.34906</y23>
			<x24>500.2677</x24>
			<y24>174.58127</y24>
			<x25>501.3764</x25>
			<y25>177.62733</y25>
			<x26>498.4703</x26>
			<y26>183.85954</y26>
			<x27>501.10208</x27>
			<y27>186.35129</y27>
			<x28>502.7651</x28>
			<y28>190.92043</y28>
			<x29>501.7964</x29>
			<y29>192.99782</y29>
			<x30>504.5681</x30>
			<y30>200.61307</y30>
			<x31>506.6455</x31>
			<y31>201.58179</y31>
			<x32>509.97156</x32>
			<y32>210.72006</y32>
			<x33>516.20374</x33>
			<y33>213.62617</y33>
			<x34>517.7268</x34>
			<y34>213.07181</y34>
			<x35>521.3272</x35>
			<y35>213.48619</y35>
			<x36>524.37335</x36>
			<y36>212.37749</y36>
			<x37>528.5281</x37>
			<y37>214.3149</y37>
			<x38>530.05115</x38>
			<y38>213.76057</y38>
			<x39>536.8321</x39>
			<y39>199.2188</y39>
			<x40>539.8782</x40>
			<y40>198.1101</y40>
			<x41>541.8156</x41>
			<y41>193.95534</y41>
			<x42>544.8617</x42>
			<y42>192.84665</y42>
		</polygon>
	</object>
	<object>
		<name>Healthy</name>
		<pose>Unspecified</pose>
		<truncated>0</truncated>
		<difficult>0</difficult>
		<occluded>0</occluded>
		<bndbox>
			<xmin>320</xmin>
			<xmax>363</xmax>
			<ymin>116</ymin>
			<ymax>171</ymax>
		</bndbox>
		<polygon>
			<x1>363.57977</x1>
			<y1>126.017265</y1>
			<x2>361.3624</x2>
			<y2>119.92505</y2>
			<x3>361.77676</x3>
			<y3>116.324615</y3>
			<x4>358.73065</x4>
			<y4>117.43331</y4>
			<x5>356.65326</x5>
			<y5>116.4646</y5>
			<x6>349.038</x6>
			<y6>119.23632</y6>
			<x7>348.0693</x7>
			<y7>121.31372</y7>
			<x8>344.46887</x8>
			<y8>120.899345</y8>
			<x9>327.71533</x9>
			<y9>126.997116</y9>
			<x10>326.7466</x10>
			<y10>129.07451</y10>
			<x11>323.70053</x11>
			<y11>130.18321</y11>
			<x12>320.7944</x12>
			<y12>136.41537</y12>
			<x13>321.9031</x13>
			<y13>139.46149</y13>
			<x14>320.9344</x14>
			<y14>141.53888</y14>
			<x15>325.9235</x15>
			<y15>155.2463</y15>
			<x16>328.00092</x16>
			<y16>156.21501</y16>
			<x17>330.21826</x17>
			<y17>162.30722</y17>
			<x18>342.68262</x18>
			<y18>168.11942</y18>
			<x19>343.79132</x19>
			<y19>171.16553</y19>
			<x20>347.39175</x20>
			<y20>171.57991</y20>
			<x21>353.48395</x21>
			<y21>169.36252</y21>
			<x22>357.35876</x22>
			<y22>161.05295</y22>
			<x23>356.25006</x23>
			<y23>158.00684</y23>
			<x24>363.031</x24>
			<y24>143.4651</y24>
			<x25>361.9223</x25>
			<y25>140.419</y25>
			<x26>362.89102</x26>
			<y26>138.3416</y26>
			<x27>361.64236</x27>
			<y27>130.17203</y27>
			<x28>363.57977</x28>
			<y28>126.017265</y28>
		</polygon>
	</object>
	<object>
		<name>Healthy</name>
		<pose>Unspecified</pose>
		<truncated>0</truncated>
		<difficult>0</difficult>
		<occluded>0</occluded>
		<bndbox>
			<xmin>286</xmin>
			<xmax>323</xmax>
			<ymin>131</ymin>
			<ymax>173</ymax>
		</bndbox>
		<polygon>
			<x1>286.5986</x1>
			<y1>160.93533</y1>
			<x2>289.23035</x2>
			<y2>163.42711</y2>
			<x3>290.33905</x3>
			<y3>166.47318</y3>
			<x4>304.88077</x4>
			<y4>173.25412</y4>
			<x5>306.40384</x5>
			<y5>172.6998</y5>
			<x6>312.49603</x6>
			<y6>170.48239</y6>
			<x7>323.1518</x7>
			<y7>147.63106</y7>
			<x8>319.27136</x8>
			<y8>136.96974</y8>
			<x9>306.807</x9>
			<y9>131.1575</y9>
			<x10>293.09958</x10>
			<y10>136.14662</y10>
			<x11>286.31863</x11>
			<y11>150.68835</y11>
			<x12>287.42734</x12>
			<y12>153.73447</y12>
			<x13>286.5986</x13>
			<y13>160.93533</y13>
		</polygon>
	</object>
	<object>
		<name>Healthy</name>
		<pose>Unspecified</pose>
		<truncated>0</truncated>
		<difficult>0</difficult>
		<occluded>0</occluded>
		<bndbox>
			<xmin>303</xmin>
			<xmax>343</xmax>
			<ymin>169</ymin>
			<ymax>215</ymax>
		</bndbox>
		<polygon>
			<x1>343.24814</x1>
			<y1>207.5843</y1>
			<x2>341.0308</x2>
			<y2>201.49213</y2>
			<x3>341.9995</x3>
			<y3>199.41473</y3>
			<x4>340.8908</x4>
			<y4>196.36862</y4>
			<x5>342.82822</x5>
			<y5>192.21385</y5>
			<x6>341.7195</x6>
			<y6>189.16776</y6>
			<x7>343.65692</x7>
			<y7>185.01294</y7>
			<x8>340.8852</x8>
			<y8>177.39774</y8>
			<x9>336.7304</x9>
			<y9>175.46033</y9>
			<x10>335.62173</x10>
			<y10>172.41422</y10>
			<x11>329.38956</x11>
			<y11>169.5081</y11>
			<x12>326.34344</x12>
			<y12>170.61679</y12>
			<x13>319.14255</x13>
			<y13>169.78809</y13>
			<x14>314.57343</x14>
			<y14>171.45111</y14>
			<x15>303.91766</x15>
			<y15>194.3024</y15>
			<x16>305.02637</x16>
			<y16>197.34851</y16>
			<x17>304.19763</x17>
			<y17>204.54942</y17>
			<x18>305.86066</x18>
			<y18>209.11856</y18>
			<x19>307.93805</x19>
			<y19>210.08727</y19>
			<x20>309.04675</x20>
			<y20>213.13333</y20>
			<x21>312.6472</x21>
			<y21>213.54771</y21>
			<x22>314.17023</x22>
			<y22>212.99335</y22>
			<x23>320.40244</x23>
			<y23>215.89946</y23>
			<x24>323.44855</x24>
			<y24>214.79082</y24>
			<x25>325.5259</x25>
			<y25>215.75948</y25>
			<x26>334.66425</x26>
			<y26>212.43343</y26>
			<x27>336.74158</x27>
			<y27>213.40213</y27>
			<x28>341.31073</x28>
			<y28>211.7391</y28>
			<x29>343.24814</x29>
			<y29>207.5843</y29>
		</polygon>
	</object>
	<object>
		<name>Healthy</name>
		<pose>Unspecified</pose>
		<truncated>0</truncated>
		<difficult>0</difficult>
		<occluded>0</occluded>
		<bndbox>
			<xmin>303</xmin>
			<xmax>338</xmax>
			<ymin>257</ymin>
			<ymax>294</ymax>
		</bndbox>
		<polygon>
			<x1>322.63098</x1>
			<y1>259.93347</y1>
			<x2>318.47623</x2>
			<y2>257.99606</y2>
			<x3>304.7688</x3>
			<y3>262.9852</y3>
			<x4>303.80008</x4>
			<y4>265.0626</y4>
			<x5>304.90872</x5>
			<y5>268.1087</y5>
			<x6>304.08002</x6>
			<y6>275.30957</y6>
			<x7>307.96045</x7>
			<y7>285.9709</y7>
			<x8>312.11523</x8>
			<y8>287.9083</y8>
			<x9>313.22394</x9>
			<y9>290.9544</y9>
			<x10>321.5335</x10>
			<y10>294.82922</y10>
			<x11>323.05655</x11>
			<y11>294.2749</y11>
			<x12>327.62567</x12>
			<y12>292.61182</y12>
			<x13>331.2261</x13>
			<y13>293.0262</y13>
			<x14>338.97577</x14>
			<y14>276.40707</y14>
			<x15>337.86707</x15>
			<y15>273.36096</y15>
			<x16>338.8358</x16>
			<y16>271.28357</y16>
			<x17>336.06406</x17>
			<y17>263.6683</y17>
			<x18>325.6771</x18>
			<y18>258.8248</y18>
			<x19>322.63098</x19>
			<y19>259.93347</y19>
		</polygon>
	</object>
	<object>
		<name>Healthy</name>
		<pose>Unspecified</pose>
		<truncated>0</truncated>
		<difficult>0</difficult>
		<occluded>0</occluded>
		<bndbox>
			<xmin>368</xmin>
			<xmax>421</xmax>
			<ymin>252</ymin>
			<ymax>298</ymax>
		</bndbox>
		<polygon>
			<x1>419.56854</x1>
			<y1>279.84515</y1>
			<x2>414.30505</x2>
			<y2>274.86163</y2>
			<x3>412.0877</x3>
			<y3>268.76944</y3>
			<x4>410.01028</x4>
			<y4>267.80075</y4>
			<x5>407.7929</x5>
			<y5>261.70853</y5>
			<x6>405.71555</x6>
			<y6>260.73984</y6>
			<x7>404.60684</x7>
			<y7>257.69376</y7>
			<x8>398.37463</x8>
			<y8>254.78764</y8>
			<x9>395.32858</x9>
			<y9>255.89635</y9>
			<x10>389.09637</x10>
			<y10>252.99022</y10>
			<x11>381.4811</x11>
			<y11>255.76193</y11>
			<x12>379.54376</x12>
			<y12>259.91672</y12>
			<x13>376.49765</x13>
			<y13>261.0254</y13>
			<x14>373.59152</x14>
			<y14>267.25757</y14>
			<x15>370.5454</x15>
			<y15>268.36627</y15>
			<x16>369.57672</x16>
			<y16>270.44366</y16>
			<x17>370.6854</x17>
			<y17>273.48978</y17>
			<x18>368.748</x18>
			<y18>277.64453</y18>
			<x19>369.8567</x19>
			<y19>280.69064</y19>
			<x20>368.88797</x20>
			<y20>282.76804</y20>
			<x21>370.551</x21>
			<y21>287.3372</y21>
			<x22>372.62842</x22>
			<y22>288.30588</y22>
			<x23>373.7371</x23>
			<y23>291.352</y23>
			<x24>388.27884</x24>
			<y24>298.1329</y24>
			<x25>389.8019</x25>
			<y25>297.57858</y25>
			<x26>393.40234</x26>
			<y26>297.99295</y26>
			<x27>396.44843</x27>
			<y27>296.88425</y27>
			<x28>398.52582</x28>
			<y28>297.85297</y28>
			<x29>403.09497</x29>
			<y29>296.18988</y29>
			<x30>404.06366</x30>
			<y30>294.11252</y30>
			<x31>416.24805</x31>
			<y31>289.67773</y31>
			<x32>421.23157</x32>
			<y32>284.41428</y32>
			<x33>419.56854</x33>
			<y33>279.84515</y33>
		</polygon>
	</object>
	<object>
		<name>Healthy</name>
		<pose>Unspecified</pose>
		<truncated>0</truncated>
		<difficult>0</difficult>
		<occluded>0</occluded>
		<bndbox>
			<xmin>495</xmin>
			<xmax>550</xmax>
			<ymin>274</ymin>
			<ymax>324</ymax>
		</bndbox>
		<polygon>
			<x1>540.1917</x1>
			<y1>322.1826</y1>
			<x2>541.1604</x2>
			<y2>320.1052</y2>
			<x3>544.2065</x3>
			<y3>318.9965</y3>
			<x4>548.08136</x4>
			<y4>310.68692</y4>
			<x5>546.9726</x5>
			<y5>307.6408</y5>
			<x6>548.91003</x6>
			<y6>303.48605</y6>
			<x7>547.8014</x7>
			<y7>300.43994</y7>
			<x8>550.70746</x8>
			<y8>294.20776</y8>
			<x9>549.5988</x9>
			<y9>291.16168</y9>
			<x10>550.5675</x10>
			<y10>289.08426</y10>
			<x11>548.9044</x11>
			<y11>284.5151</y11>
			<x12>546.8271</x12>
			<y12>283.54642</y12>
			<x13>542.5323</x13>
			<y13>276.48553</y13>
			<x14>538.3775</x14>
			<y14>274.54813</y14>
			<x15>535.3314</x15>
			<y15>275.65677</y15>
			<x16>533.254</x16>
			<y16>274.68808</y16>
			<x17>530.2079</x17>
			<y17>275.79675</y17>
			<x18>523.007</x18>
			<y18>274.96805</y18>
			<x19>509.29962</x19>
			<y19>279.95718</y19>
			<x20>508.3309</x20>
			<y20>282.03458</y20>
			<x21>505.2848</x21>
			<y21>283.14322</y21>
			<x22>501.40997</x22>
			<y22>291.4528</y22>
			<x23>498.36386</x23>
			<y23>292.5615</y23>
			<x24>497.3952</x24>
			<y24>294.6389</y24>
			<x25>498.50385</x25>
			<y25>297.685</y25>
			<x26>495.59775</x26>
			<y26>303.91714</y26>
			<x27>501.69556</x27>
			<y27>320.6707</y27>
			<x28>510.00513</x28>
			<y28>324.5455</y28>
			<x29>511.52814</x29>
			<y29>323.99118</y29>
			<x30>515.1286</x30>
			<y30>324.40552</y30>
			<x31>518.1747</x31>
			<y31>323.2968</y31>
			<x32>520.2521</x32>
			<y32>324.26553</y32>
			<x33>526.3443</x33>
			<y33>322.0482</y33>
			<x34>528.4217</x34>
			<y34>323.01688</y34>
			<x35>531.4678</x35>
			<y35>321.9082</y35>
			<x36>535.62256</x36>
			<y36>323.8456</y36>
			<x37>540.1917</x37>
			<y37>322.1826</y37>
		</polygon>
	</object>
	<object>
		<name>Healthy</name>
		<pose>Unspecified</pose>
		<truncated>0</truncated>
		<difficult>0</difficult>
		<occluded>0</occluded>
		<bndbox>
			<xmin>382</xmin>
			<xmax>423</xmax>
			<ymin>227</ymin>
			<ymax>260</ymax>
		</bndbox>
		<polygon>
			<x1>398.64343</x1>
			<y1>227.09277</y1>
			<x2>387.9821</x2>
			<y2>230.97319</y2>
			<x3>387.0134</x3>
			<y3>233.0506</y3>
			<x4>383.96732</x4>
			<y4>234.15929</y4>
			<x5>382.0299</x5>
			<y5>238.31406</y5>
			<x6>387.019</x6>
			<y6>252.02151</y6>
			<x7>397.4059</x7>
			<y7>256.86505</y7>
			<x8>398.92902</x8>
			<y8>256.31067</y8>
			<x9>400.45203</x9>
			<y9>255.75635</y9>
			<x10>410.83902</x10>
			<y10>260.59988</y10>
			<x11>415.40814</x11>
			<y11>258.9368</y11>
			<x12>416.37686</x12>
			<y12>256.85944</y12>
			<x13>419.42297</x13>
			<y13>255.75075</y13>
			<x14>423.2978</x14>
			<y14>247.4412</y14>
			<x15>419.41736</x15>
			<y15>236.77983</y15>
			<x16>398.64343</x16>
			<y16>227.09277</y16>
		</polygon>
	</object>
	<object>
		<name>Healthy</name>
		<pose>Unspecified</pose>
		<truncated>0</truncated>
		<difficult>0</difficult>
		<occluded>0</occluded>
		<bndbox>
			<xmin>394</xmin>
			<xmax>441</xmax>
			<ymin>202</ymin>
			<ymax>235</ymax>
		</bndbox>
		<polygon>
			<x1>415.39136</x1>
			<y1>202.02408</y1>
			<x2>404.73004</x2>
			<y2>205.9045</y2>
			<x3>403.76135</x3>
			<y3>207.9819</y3>
			<x4>400.71524</x4>
			<y4>209.09059</y4>
			<x5>394.903</x5>
			<y5>221.55493</y5>
			<x6>396.56604</x6>
			<y6>226.12407</y6>
			<x7>417.33997</x7>
			<y7>235.81113</y7>
			<x8>418.863</x8>
			<y8>235.25679</y8>
			<x9>424.95523</x9>
			<y9>233.0394</y9>
			<x10>427.86133</x10>
			<y10>226.80724</y10>
			<x11>440.04572</x11>
			<y11>222.37245</y11>
			<x12>441.98312</x12>
			<y12>218.2177</y12>
			<x13>439.21143</x13>
			<y13>210.60245</y13>
			<x14>435.0566</x14>
			<y14>208.66502</y14>
			<x15>432.0105</x15>
			<y15>209.77373</y15>
			<x16>415.39136</x16>
			<y16>202.02408</y16>
		</polygon>
	</object>
	<object>
		<name>Healthy</name>
		<pose>Unspecified</pose>
		<truncated>0</truncated>
		<difficult>0</difficult>
		<occluded>0</occluded>
		<bndbox>
			<xmin>463</xmin>
			<xmax>504</xmax>
			<ymin>217</ymin>
			<ymax>259</ymax>
		</bndbox>
		<polygon>
			<x1>501.11325</x1>
			<y1>224.29309</y1>
			<x2>486.57147</x2>
			<y2>217.51219</y2>
			<x3>480.4793</x3>
			<y3>219.72954</y3>
			<x4>478.40192</x4>
			<y4>218.76083</y4>
			<x5>473.83276</x5>
			<y5>220.42386</y5>
			<x6>472.86407</x6>
			<y6>222.50127</y6>
			<x7>469.81796</x7>
			<y7>223.60995</y7>
			<x8>467.88052</x8>
			<y8>227.76476</y8>
			<x9>464.83444</x9>
			<y9>228.87341</y9>
			<x10>463.86572</x10>
			<y10>230.9508</y10>
			<x11>464.97443</x11>
			<y11>233.99692</y11>
			<x12>463.03702</x12>
			<y12>238.15172</y12>
			<x13>466.91742</x13>
			<y13>248.81303</y13>
			<x14>468.99484</x14>
			<y14>249.78175</y14>
			<x15>470.10352</x15>
			<y15>252.82787</y15>
			<x16>484.64526</x16>
			<y16>259.6088</y16>
			<x17>486.1683</x17>
			<y17>259.0544</y17>
			<x18>498.3527</x18>
			<y18>254.61967</y18>
			<x19>501.2588</x19>
			<y19>248.38751</y19>
			<x20>500.15015</x20>
			<y20>245.34142</y20>
			<x21>501.1188</x21>
			<y21>243.264</y21>
			<x22>504.16492</x22>
			<y22>242.1553</y22>
			<x23>503.0562</x23>
			<y23>239.1092</y23>
			<x24>503.88498</x24>
			<y24>231.90834</y24>
			<x25>501.11325</x25>
			<y25>224.29309</y25>
		</polygon>
	</object>
	<object>
		<name>Healthy</name>
		<pose>Unspecified</pose>
		<truncated>0</truncated>
		<difficult>0</difficult>
		<occluded>0</occluded>
		<bndbox>
			<xmin>496</xmin>
			<xmax>555</xmax>
			<ymin>235</ymin>
			<ymax>324</ymax>
		</bndbox>
		<polygon>
			<x1>538.66864</x1>
			<y1>322.7369</y1>
			<x2>541.1604</x2>
			<y2>320.1052</y2>
			<x3>544.2065</x3>
			<y3>318.9965</y3>
			<x4>548.08136</x4>
			<y4>310.68692</y4>
			<x5>546.9726</x5>
			<y5>307.6408</y5>
			<x6>549.8788</x6>
			<y6>301.40866</y6>
			<x7>548.7701</x7>
			<y7>298.36255</y7>
			<x8>550.70746</x8>
			<y8>294.20776</y8>
			<x9>546.8271</x9>
			<y9>283.54642</y9>
			<x10>544.7497</x10>
			<y10>282.5777</y10>
			<x11>543.641</x11>
			<y11>279.53162</y11>
			<x12>536.4401</x12>
			<y12>278.70288</y12>
			<x13>534.77704</x13>
			<y13>274.13373</y13>
			<x14>543.91534</x14>
			<y14>270.8077</y14>
			<x15>544.8841</x15>
			<y15>268.7303</y15>
			<x16>551.94495</x16>
			<y16>264.4355</y16>
			<x17>552.91364</x17>
			<y17>262.35815</y17>
			<x18>551.805</x18>
			<y18>259.31204</y18>
			<x19>555.6798</x19>
			<y19>251.00247</y19>
			<x20>552.9081</x20>
			<y20>243.38722</y20>
			<x21>548.7533</x21>
			<y21>241.44981</y21>
			<x22>547.6446</x22>
			<y22>238.4037</y22>
			<x23>541.4124</x23>
			<y23>235.49757</y23>
			<x24>538.36633</x24>
			<y24>236.60628</y24>
			<x25>536.28894</x25>
			<y25>235.63757</y25>
			<x26>533.2428</x26>
			<y26>236.74626</y26>
			<x27>526.04193</x27>
			<y27>235.91756</y27>
			<x28>518.4267</x28>
			<y28>238.68927</y28>
			<x29>515.52057</x29>
			<y29>244.92143</y29>
			<x30>516.6293</x30>
			<y30>247.96754</y30>
			<x31>513.72314</x31>
			<y31>254.1997</y31>
			<x32>514.83185</x32>
			<y32>257.24582</y32>
			<x33>512.8945</x33>
			<y33>261.40063</y33>
			<x34>506.80225</x34>
			<y34>263.61798</y34>
			<x35>502.92746</x35>
			<y35>271.92755</y35>
			<x36>504.0361</x36>
			<y36>274.97363</y36>
			<x37>502.0987</x37>
			<y37>279.12845</y37>
			<x38>503.34738</x38>
			<y38>287.29803</y38>
			<x39>500.44128</x39>
			<y39>293.53018</y39>
			<x40>497.3952</x40>
			<y40>294.6389</y40>
			<x41>498.50385</x41>
			<y41>297.685</y41>
			<x42>496.56644</x42>
			<y42>301.83975</y42>
			<x43>497.67514</x43>
			<y43>304.88586</y43>
			<x44>496.70645</x44>
			<y44>306.96326</y44>
			<x45>500.58685</x45>
			<y45>317.62463</y45>
			<x46>502.66425</x46>
			<y46>318.5933</y46>
			<x47>503.77295</x47>
			<y47>321.6394</y47>
			<x48>507.9277</x48>
			<y48>323.5768</y48>
			<x49>509.45078</x49>
			<y49>323.0225</y49>
			<x50>510.97382</x50>
			<y50>322.4681</y50>
			<x51>515.1286</x51>
			<y51>324.40552</y51>
			<x52>518.1747</x52>
			<y52>323.2968</y52>
			<x53>520.2521</x53>
			<y53>324.26553</y53>
			<x54>526.3443</x54>
			<y54>322.0482</y54>
			<x55>530.4991</x55>
			<y55>323.9856</y55>
			<x56>536.5913</x56>
			<y56>321.76822</y56>
			<x57>538.66864</x57>
			<y57>322.7369</y57>
		</polygon>
	</object>
	<object>
		<name>Healthy</name>
		<pose>Unspecified</pose>
		<truncated>0</truncated>
		<difficult>0</difficult>
		<occluded>0</occluded>
		<bndbox>
			<xmin>690</xmin>
			<xmax>750</xmax>
			<ymin>164</ymin>
			<ymax>221</ymax>
		</bndbox>
		<polygon>
			<x1>749.6613</x1>
			<y1>182.12376</y1>
			<x2>750.63</x2>
			<y2>180.0464</y2>
			<x3>749.5213</x3>
			<y3>177.00029</y3>
			<x4>750.49</x4>
			<y4>174.92288</y4>
			<x5>748.827</x5>
			<y5>170.35374</y5>
			<x6>736.3626</x6>
			<y6>164.5415</y6>
			<x7>722.65515</x7>
			<y7>169.53062</y7>
			<x8>717.6717</x8>
			<y8>174.79408</y8>
			<x9>713.10254</x9>
			<y9>176.4571</y9>
			<x10>708.94775</x10>
			<y10>174.51974</y10>
			<x11>698.2864</x11>
			<y11>178.40012</y11>
			<x12>690.53674</x12>
			<y12>195.01929</y12>
			<x13>691.6455</x13>
			<y13>198.06535</y13>
			<x14>690.67676</x14>
			<y14>200.14275</y14>
			<x15>697.88324</x15>
			<y15>219.9424</y15>
			<x16>702.038</x16>
			<y16>221.8798</y16>
			<x17>703.56104</x17>
			<y17>221.32542</y17>
			<x18>707.1615</x18>
			<y18>221.73982</y18>
			<x19>726.9612</x19>
			<y19>214.53336</y19>
			<x20>728.89856</x20>
			<y20>210.37856</y20>
			<x21>731.94464</x21>
			<y21>209.26985</y21>
			<x22>735.81946</x22>
			<y22>200.96028</y22>
			<x23>738.8656</x23>
			<y23>199.8516</y23>
			<x24>746.6152</x24>
			<y24>183.23245</y24>
			<x25>749.6613</x25>
			<y25>182.12376</y25>
		</polygon>
	</object>
	<object>
		<name>Healthy</name>
		<pose>Unspecified</pose>
		<truncated>0</truncated>
		<difficult>0</difficult>
		<occluded>0</occluded>
		<bndbox>
			<xmin>617</xmin>
			<xmax>656</xmax>
			<ymin>2</ymin>
			<ymax>40</ymax>
		</bndbox>
		<polygon>
			<x3>622.76685</x3>
			<y3>4.083873</y3>
			<x4>619.7207</x4>
			<y4>5.1925383</y4>
			<x5>620.8294</x5>
			<y5>8.238656</y5>
			<x6>617.9233</x6>
			<y6>14.470811</y6>
			<x7>620.1406</x7>
			<y7>20.56301</y7>
			<x8>619.172</x8>
			<y8>22.640419</y8>
			<x9>620.28064</x9>
			<y9>25.686499</y9>
			<x10>619.31195</x10>
			<y10>27.76391</y10>
			<x11>621.5293</x11>
			<y11>33.85609</y11>
			<x12>620.5606</x12>
			<y12>35.93348</y12>
			<x13>621.1149</x13>
			<y13>37.45653</y13>
			<x14>624.161</x14>
			<y14>36.34785</y14>
			<x15>626.2384</x15>
			<y15>37.316555</y15>
			<x16>627.34717</x16>
			<y16>40.36265</y16>
			<x17>628.8701</x17>
			<y17>39.808292</y17>
			<x18>641.05457</x18>
			<y18>35.373558</y18>
			<x19>642.02325</x19>
			<y19>33.29615</y19>
			<x20>645.0694</x20>
			<y20>32.187485</y20>
			<x21>656.69385</x21>
			<y21>7.2587657</y21>
			<x22>655.58514</x22>
			<y22>4.2126484</y22>
			<x23>656.55383</x23>
			<y23>2.1352756</y23>
			</polygon>
	</object>
	<object>
		<name>Healthy</name>
		<pose>Unspecified</pose>
		<truncated>0</truncated>
		<difficult>0</difficult>
		<occluded>0</occluded>
		<bndbox>
			<xmin>697</xmin>
			<xmax>736</xmax>
			<ymin>70</ymin>
			<ymax>111</ymax>
		</bndbox>
		<polygon>
			<x1>719.4411</x1>
			<y1>70.66127</y1>
			<x2>705.7337</x2>
			<y2>75.650345</y2>
			<x3>697.9841</x3>
			<y3>92.26948</y3>
			<x4>699.0928</x4>
			<y4>95.3156</y4>
			<x5>698.124</x5>
			<y5>97.39299</y5>
			<x6>699.7871</x6>
			<y6>101.962135</y6>
			<x7>701.8645</x7>
			<y7>102.93084</y7>
			<x8>702.97314</x8>
			<y8>105.976944</y8>
			<x9>715.43756</x9>
			<y9>111.78919</y9>
			<x10>716.9606</x10>
			<y10>111.23481</y10>
			<x11>723.0528</x11>
			<y11>109.01746</y11>
			<x12>724.9902</x12>
			<y12>104.862656</y12>
			<x13>728.03625</x13>
			<y13>103.75396</y13>
			<x14>736.75464</x14>
			<y14>85.057434</y14>
			<x15>735.09155</x15>
			<y15>80.48828</y15>
			<x16>733.01416</x16>
			<y16>79.51958</y16>
			<x17>731.9055</x17>
			<y17>76.47347</y17>
			<x18>719.4411</x18>
			<y18>70.66127</y18>
		</polygon>
	</object>
	<object>
		<name>Healthy</name>
		<pose>Unspecified</pose>
		<truncated>0</truncated>
		<difficult>0</difficult>
		<occluded>0</occluded>
		<bndbox>
			<xmin>650</xmin>
			<xmax>702</xmax>
			<ymin>2</ymin>
			<ymax>64</ymax>
		</bndbox>
		<polygon>
			<x1>694.9489</x1>
			<y1>43.551804</y1>
			<x2>702.88055</x2>
			<y2>25.048761</y2>
			<x3>698.21594</x3>
			<y3>14.1476965</y3>
			<x4>684.6717</x4>
			<y4>5.5103817</y4>
			<x5>676.5181</x5>
			<y5>2.2286518</y5>
			<x6>658.022</x6>
			<y6>13.2009535</y6>
			<x7>651.43427</x7>
			<y7>31.591557</y7>
			<x8>650.1161</x8>
			<y8>50.98506</y8>
			<x9>652.3495</x9>
			<y9>62.396164</y9>
			<x10>665.23816</x10>
			<y10>64.2274</y10>
			<x11>674.2263</x11>
			<y11>60.712135</y11>
			<x12>684.695</x12>
			<y12>49.24938</y12>
			<x13>694.9489</x13>
			<y13>43.551804</y13>
		</polygon>
	</object>
	<object>
		<name>Healthy</name>
		<pose>Unspecified</pose>
		<truncated>0</truncated>
		<difficult>0</difficult>
		<occluded>0</occluded>
		<bndbox>
			<xmin>723</xmin>
			<xmax>763</xmax>
			<ymin>75</ymin>
			<ymax>128</ymax>
		</bndbox>
		<polygon>
			<x1>723.5332</x1>
			<y1>106.36316</y1>
			<x2>741.4306</x2>
			<y2>128.57948</y2>
			<x3>759.32056</x3>
			<y3>127.67461</y3>
			<x7>763.29785</x7>
			<y7>75.07446</y7>
			<x8>745.4648</x8>
			<y8>78.060715</y8>
			<x9>735.59546</x9>
			<y9>90.41148</y9>
			<x10>723.5332</x10>
			<y10>106.36316</y10>
		</polygon>
	</object>
	<object>
		<name>Healthy</name>
		<pose>Unspecified</pose>
		<truncated>0</truncated>
		<difficult>0</difficult>
		<occluded>0</occluded>
		<bndbox>
			<xmin>719</xmin>
			<xmax>764</xmax>
			<ymin>30</ymin>
			<ymax>81</ymax>
		</bndbox>
		<polygon>
			<x4>761.4549</x4>
			<y4>30.548544</y4>
			<x5>751.58307</x5>
			<y5>35.19226</y5>
			<x6>736.4449</x6>
			<y6>32.79333</y6>
			<x7>727.2257</x7>
			<y7>43.355785</y7>
			<x8>721.1209</x8>
			<y8>41.022762</y8>
			<x9>721.32513</x9>
			<y9>63.7219</y9>
			<x10>719.35754</x10>
			<y10>67.941605</y10>
			<x11>737.22406</x11>
			<y11>81.41016</y11>
			<x12>754.1845</x12>
			<y12>76.98956</y12>
			<x13>764.5922</x13>
			<y13>76.70553</y13>
			</polygon>
	</object>
	<object>
		<name>Healthy</name>
		<pose>Unspecified</pose>
		<truncated>0</truncated>
		<difficult>0</difficult>
		<occluded>0</occluded>
		<bndbox>
			<xmin>741</xmin>
			<xmax>767</xmax>
			<ymin>129</ymin>
			<ymax>174</ymax>
		</bndbox>
		<polygon>
			<x1>755.8331</x1>
			<y1>129.64447</y1>
			<x2>741.6039</x2>
			<y2>142.53079</y2>
			<x3>748.24963</x3>
			<y3>164.63756</y3>
			<x4>752.89417</x4>
			<y4>174.50919</y4>
			<x5>755.7912</x5>
			<y5>173.80528</y5>
			<x6>763.80176</x6>
			<y6>154.42307</y6>
			<x7>767.1728</x7>
			<y7>140.58327</y7>
			<x11>755.8331</x11>
			<y11>129.64447</y11>
		</polygon>
	</object>
	<object>
		<name>Healthy</name>
		<pose>Unspecified</pose>
		<truncated>0</truncated>
		<difficult>0</difficult>
		<occluded>0</occluded>
		<bndbox>
			<xmin>424</xmin>
			<xmax>457</xmax>
			<ymin>225</ymin>
			<ymax>259</ymax>
		</bndbox>
		<polygon>
			<x1>443.88318</x1>
			<y1>259.1799</y1>
			<x2>456.82047</x2>
			<y2>252.36954</y2>
			<x3>457.29437</x3>
			<y3>239.2337</y3>
			<x4>450.7935</x4>
			<y4>230.0376</y4>
			<x5>436.08035</x5>
			<y5>225.23163</y5>
			<x6>424.71722</x6>
			<y6>228.66621</y6>
			<x7>426.3971</x7>
			<y7>247.2686</y7>
			<x8>443.88318</x8>
			<y8>259.1799</y8>
		</polygon>
	</object>
	<object>
		<name>Healthy</name>
		<pose>Unspecified</pose>
		<truncated>0</truncated>
		<difficult>0</difficult>
		<occluded>0</occluded>
		<bndbox>
			<xmin>596</xmin>
			<xmax>641</xmax>
			<ymin>285</ymin>
			<ymax>315</ymax>
		</bndbox>
		<polygon>
			<x1>623.92633</x1>
			<y1>307.17465</y1>
			<x2>641.8508</x2>
			<y2>297.63593</y2>
			<x3>639.7297</x3>
			<y3>290.9126</y3>
			<x4>632.6955</x4>
			<y4>285.06384</y4>
			<x5>620.00934</x5>
			<y5>285.82663</y5>
			<x6>608.33813</x6>
			<y6>293.2274</y6>
			<x7>596.4156</x7>
			<y7>306.67563</y7>
			<x8>602.0725</x8>
			<y8>315.47815</y8>
			<x9>611.43945</x9>
			<y9>315.22253</y9>
			<x10>623.92633</x10>
			<y10>307.17465</y10>
		</polygon>
	</object>
	<object>
		<name>Healthy</name>
		<pose>Unspecified</pose>
		<truncated>0</truncated>
		<difficult>0</difficult>
		<occluded>0</occluded>
		<bndbox>
			<xmin>282</xmin>
			<xmax>322</xmax>
			<ymin>39</ymin>
			<ymax>83</ymax>
		</bndbox>
		<polygon>
			<x1>284.32077</x1>
			<y1>46.069164</y1>
			<x2>282.80856</x2>
			<y2>66.94047</y2>
			<x3>294.18634</x3>
			<y3>78.993744</y3>
			<x4>300.53522</x4>
			<y4>82.912384</y4>
			<x5>317.21613</x5>
			<y5>83.49862</y5>
			<x6>322.47186</x6>
			<y6>70.02404</y6>
			<x7>320.10315</x7>
			<y7>51.966568</y7>
			<x8>319.4819</x8>
			<y8>44.484722</y8>
			<x9>306.87872</x9>
			<y9>40.662636</y9>
			<x10>292.6729</x10>
			<y10>39.175613</y10>
			<x11>284.32077</x11>
			<y11>46.069164</y11>
		</polygon>
	</object>
	<object>
		<name>Healthy</name>
		<pose>Unspecified</pose>
		<truncated>0</truncated>
		<difficult>0</difficult>
		<occluded>0</occluded>
		<bndbox>
			<xmin>223</xmin>
			<xmax>259</xmax>
			<ymin>218</ymin>
			<ymax>259</ymax>
		</bndbox>
		<polygon>
			<x1>247.47035</x1>
			<y1>252.90079</y1>
			<x2>250.94789</x2>
			<y2>259.87527</y2>
			<x3>257.904</x3>
			<y3>245.95049</y3>
			<x4>259.16757</x4>
			<y4>238.83379</y4>
			<x5>242.7354</x5>
			<y5>224.49292</y5>
			<x6>227.37497</x6>
			<y6>218.87144</y6>
			<x7>223.74771</x7>
			<y7>223.34468</y7>
			<x8>230.2486</x8>
			<y8>232.5408</y8>
			<x9>237.81868</x9>
			<y9>242.7492</y9>
			<x10>247.47035</x10>
			<y10>252.90079</y10>
		</polygon>
	</object>
	<object>
		<name>Healthy</name>
		<pose>Unspecified</pose>
		<truncated>0</truncated>
		<difficult>0</difficult>
		<occluded>0</occluded>
		<bndbox>
			<xmin>215</xmin>
			<xmax>275</xmax>
			<ymin>129</ymin>
			<ymax>200</ymax>
		</bndbox>
		<polygon>
			<x1>269.2751</x1>
			<y1>143.3393</y1>
			<x2>254.36264</x2>
			<y2>131.24823</y2>
			<x3>242.0132</x3>
			<y3>129.08565</y3>
			<x4>225.89917</x4>
			<y4>141.60681</y4>
			<x5>229.39409</x5>
			<y5>162.75806</y5>
			<x6>222.11118</x6>
			<y6>170.66391</y6>
			<x7>215.9285</x7>
			<y7>188.32985</y7>
			<x8>222.31544</x8>
			<y8>193.36305</y8>
			<x9>230.53029</x9>
			<y9>196.67998</y9>
			<x10>243.55548</x10>
			<y10>200.69878</y10>
			<x11>253.90627</x11>
			<y11>198.33331</y11>
			<x12>260.2313</x12>
			<y12>185.871</y12>
			<x13>275.30704</x13>
			<y13>181.08527</y13>
			<x14>274.76868</x14>
			<y14>169.01859</y14>
			<x15>269.2751</x15>
			<y15>143.3393</y15>
		</polygon>
	</object>
	<object>
		<name>Healthy</name>
		<pose>Unspecified</pose>
		<truncated>0</truncated>
		<difficult>0</difficult>
		<occluded>0</occluded>
		<bndbox>
			<xmin>251</xmin>
			<xmax>299</xmax>
			<ymin>103</ymin>
			<ymax>147</ymax>
		</bndbox>
		<polygon>
			<x1>288.6178</x1>
			<y1>111.774704</y1>
			<x2>274.04443</x2>
			<y2>104.465324</y2>
			<x3>262.14545</x3>
			<y3>103.54025</y3>
			<x4>255.82042</x4>
			<y4>116.00256</y4>
			<x5>251.85666</x5>
			<y5>121.55943</y5>
			<x6>268.0066</x6>
			<y6>135.0419</y6>
			<x7>277.40454</x7>
			<y7>143.53403</y7>
			<x8>287.08212</x8>
			<y8>147.01933</y8>
			<x9>291.55338</x9>
			<y9>142.93962</y9>
			<x10>295.09518</x10>
			<y10>135.34415</y10>
			<x11>299.45508</x11>
			<y11>134.80855</y11>
			<x12>292.92578</x12>
			<y12>124.571724</y12>
			<x13>288.6178</x13>
			<y13>111.774704</y13>
		</polygon>
	</object>
</annotation>